{
  "slug": "openclaw-setup",
  "title": "OpenClaw Setup & Support - Promo 50% Setup",
  "price": "3 gói tùy chọn",
  "tags": [
    "openclaw",
    "setup",
    "automation",
    "promo"
  ],
  "notes": "🎉 PROMO: 50% OFF phí setup cho 25 khách đầu tiên (kết thúc khi group đạt 100 members)\n\n✅ 7-day 100% refund cho phí setup\n✅ SLA 99.5% uptime\n✅ Hỗ trợ technical 24/7 qua Zalo\n\n⚠️ OVERAGE POLICY:\n• Vượt quota: 100k/giờ hoặc 200k/buổi (1 buổi = 2 giờ)\n• Quy tắc làm tròn: Làm tròn xuống (floor)\n• Ví dụ 1: Gói Lite vượt 1.8 giờ → tính 1 giờ × 100k = 100k\n• Ví dụ 2: Gói Standard vượt 3.5 giờ → tính 3 giờ × 100k = 300k (hoặc 1 buổi × 200k = 200k, chọn rẻ hơn)",
  "items": [
    {
      "title": "OpenClaw Lite",
      "retail": 600000,
      "cost": 1200000,
      "duration": "390k/tháng",
      "notes": "Phù hợp cho cá nhân và startup nhỏ"
    },
    {
      "title": "OpenClaw Standard",
      "retail": 900000,
      "cost": 1800000,
      "duration": "690k/tháng",
      "notes": "Phù hợp cho SME và team nhỏ"
    },
    {
      "title": "OpenClaw Pro",
      "retail": 1250000,
      "cost": 2500000,
      "duration": "990k/tháng",
      "notes": "Phù hợp cho enterprise và scale-up"
    }
  ]
}
